dopai/__init__.py
dopai/predictor.py
dopai-0.1.2.dist-info/METADATA
dopai-0.1.2.dist-info/WHEEL
dopai-0.1.2.dist-info/RECORD
