Metadata-Version: 2.4
Name: dopai
Version: 0.1.2
Summary: DOPai is an intelligent medical assistance tool and leverages artificial intelligence technology to assist clinical doctors in diagnosing diabetes complicated with osteoporosis. The tool classifies diabetic patients into the "low bone mass/normal bone mass group" or the "osteoporosis/severe osteoporosis group" using 12 clinical features of diabetic patients.
Author: ycj
Author-email: yanchangjian2019@126.com
Requires-Python: >=3.7
Classifier: Programming Language :: Python :: 3
Classifier: Programming Language :: Python :: 3.7
Classifier: Programming Language :: Python :: 3.8
Classifier: Programming Language :: Python :: 3.9
Classifier: Programming Language :: Python :: 3.10
Classifier: Programming Language :: Python :: 3.11
Classifier: Programming Language :: Python :: 3.12
Classifier: Programming Language :: Python :: 3.13
Classifier: Programming Language :: Python :: 3.14
